relations_mysql/__init__.py
relations_mysql/clause.py
relations_mysql/column.py
relations_mysql/criteria.py
relations_mysql/criterion.py
relations_mysql/ddl.py
relations_mysql/expression.py
relations_mysql/index.py
relations_mysql/query.py
relations_mysql/sql.py
relations_mysql/table.py
relations_mysql-0.6.3.dist-info/LICENSE.txt
relations_mysql-0.6.3.dist-info/METADATA
relations_mysql-0.6.3.dist-info/WHEEL
relations_mysql-0.6.3.dist-info/top_level.txt
relations_mysql-0.6.3.dist-info/RECORD
