Metadata-Version: 2.1
Name: relations-mysql
Version: 0.6.3
Home-page: https://github.com/relations-dil/python-relations-mysql
Author: Gaffer Fitch
Author-email: relations@gaf3.com
Classifier: Programming Language :: Python :: 3
Classifier: License :: OSI Approved :: MIT License
License-File: LICENSE.txt
Requires-Dist: relations-sql (>=0.6.7)
